loggify/__init__.py
loggify/logger.py
loggify-0.2.1.dist-info/LICENSE
loggify-0.2.1.dist-info/METADATA
loggify-0.2.1.dist-info/WHEEL
loggify-0.2.1.dist-info/top_level.txt
loggify-0.2.1.dist-info/RECORD
