Metadata-Version: 2.1
Name: loggify
Version: 0.2.1
Summary: Capture prints and tracebacks to a log file with 2 lines of code
Home-page: https://github.com/ar-nowaczynski/loggify
Author: Arkadiusz Nowaczyński
Author-email: ar.nowaczynski@gmail.com
License: MIT
Platform: UNKNOWN
Classifier: License :: OSI Approved :: MIT License
Classifier: Programming Language :: Python :: 3
Classifier: Programming Language :: Python :: 3.7
Classifier: Programming Language :: Python :: 3.8
Classifier: Programming Language :: Python :: 3.9
Requires-Python: >=3.7
